SBOMVis/__init__.py
SBOMVis/surfactantplugin_sbomvis.py
SBOMVis/visualization.py
SBOMVis/customTemplates/template.html
SBOMVis/customTemplates/assets/surfactant-logo-dark.png
SBOMVis/customTemplates/src/buttonEventHandlers.js
SBOMVis/customTemplates/src/kvGraph.js
SBOMVis/customTemplates/src/main.css
SBOMVis/customTemplates/src/main.js
SBOMVis/customTemplates/src/mouseEventHandlers.js
SBOMVis/customTemplates/src/popup.js
SBOMVis/customTemplates/src/sidebar.js
SBOMVis/customTemplates/src/utils.js
sbomvis-0.0.0rc16.dist-info/METADATA
sbomvis-0.0.0rc16.dist-info/WHEEL
sbomvis-0.0.0rc16.dist-info/entry_points.txt
sbomvis-0.0.0rc16.dist-info/top_level.txt
sbomvis-0.0.0rc16.dist-info/RECORD
