Metadata-Version: 2.4
Name: sbomvis
Version: 0.0.0rc16
Summary: Surfactant SBOM Visualization
Author-email: Joseph Hand <hand8@llnl.gov>
License: MIT License
Keywords: surfactant
Classifier: Programming Language :: Python :: 3
Classifier: Environment :: Console
Classifier: Operating System :: MacOS
Classifier: Operating System :: Microsoft :: Windows
Classifier: Operating System :: POSIX :: Linux
Classifier: License :: OSI Approved :: MIT License
Requires-Python: >=3.9
Requires-Dist: dataclasses_json
Requires-Dist: Jinja2
Requires-Dist: loguru
Requires-Dist: networkx
Requires-Dist: pyvis
Requires-Dist: surfactant
